LICENSE
README.rst
setup.py
sqliteio/__init__.py
sqliteio/btree.py
sqliteio/pager.py
sqliteio/record.py
sqliteio/schema.py
sqliteio.egg-info/PKG-INFO
sqliteio.egg-info/SOURCES.txt
sqliteio.egg-info/dependency_links.txt
sqliteio.egg-info/top_level.txt