Metadata-Version: 2.1
Name: sqliteio
Version: 0.2.0
Summary: SQLite3 I/O library
Home-page: https://github.com/nakagami/sqliteio/
Author: Hajime Nakagami
Author-email: nakagami@gmail.com
License: MIT
Keywords: SQLite3
Platform: UNKNOWN
Classifier: Development Status :: 3 - Alpha
Classifier: License :: OSI Approved :: MIT License
Classifier: Operating System :: OS Independent
Classifier: Programming Language :: Python
Classifier: Programming Language :: Python :: 3
Classifier: Topic :: Database
License-File: LICENSE
